cricket/__init__.py
cricket/combined.py
cricket/utils.py
cricket/balling/__init__.py
cricket/balling/fast.py
cricket/balling/overall_bowl_detection.py
cricket/balling/slow.py
cricket/balling/spin.py
cricket/balling/yorker.py
cricket/batting/__init__.py
cricket/batting/cover_drive.py
cricket/batting/defense.py
cricket/batting/hook_shot.py
cricket/batting/overall_shot_detection.py
cricket/batting/pull_shot.py
cricket/batting/reverse_sweep.py
cricket/batting/straight_drive.py
cricket/batting/sweep.py
cricket_tannmay-0.1.6.dist-info/METADATA
cricket_tannmay-0.1.6.dist-info/WHEEL
cricket_tannmay-0.1.6.dist-info/top_level.txt
cricket_tannmay-0.1.6.dist-info/RECORD
