Metadata-Version: 2.4
Name: cricket-tannmay
Version: 0.1.6
Summary: A computer vision package to recognize and assess different cricket shots and bowling videos.
Author-email: Tannmay Khandelwal <tannmaykhandelwal@gmail.com>
License: MIT License
Classifier: Development Status :: 4 - Beta
Classifier: Intended Audience :: Developers
Classifier: Topic :: Software Development :: Libraries :: Python Modules
Classifier: Programming Language :: Python :: 3
Classifier: Operating System :: OS Independent
Requires-Python: >=3.6
Requires-Dist: absl-py==2.1.0
Requires-Dist: altair==5.4.1
Requires-Dist: astunparse==1.6.3
Requires-Dist: attrs==24.2.0
Requires-Dist: blinker==1.8.2
Requires-Dist: cachetools==5.5.0
Requires-Dist: certifi==2024.8.30
Requires-Dist: cffi==1.17.1
Requires-Dist: charset-normalizer==3.4.0
Requires-Dist: click==8.1.7
Requires-Dist: colorama==0.4.6
Requires-Dist: contourpy==1.3.0
Requires-Dist: cycler==0.12.1
Requires-Dist: flatbuffers==24.3.25
Requires-Dist: fonttools==4.54.1
Requires-Dist: gast==0.6.0
Requires-Dist: gitdb==4.0.11
Requires-Dist: GitPython==3.1.43
Requires-Dist: google-pasta==0.2.0
Requires-Dist: grpcio==1.66.2
Requires-Dist: h5py==3.12.1
Requires-Dist: idna==3.10
Requires-Dist: jax==0.4.34
Requires-Dist: jaxlib==0.4.34
Requires-Dist: Jinja2==3.1.4
Requires-Dist: jsonschema==4.23.0
Requires-Dist: jsonschema-specifications==2024.10.1
Requires-Dist: keras==3.6.0
Requires-Dist: kiwisolver==1.4.7
Requires-Dist: libclang==18.1.1
Requires-Dist: Markdown==3.7
Requires-Dist: markdown-it-py==3.0.0
Requires-Dist: MarkupSafe==3.0.1
Requires-Dist: matplotlib==3.9.2
Requires-Dist: mdurl==0.1.2
Requires-Dist: mediapipe==0.10.11
Requires-Dist: ml-dtypes==0.4.1
Requires-Dist: namex==0.0.8
Requires-Dist: narwhals==1.9.3
Requires-Dist: numpy==1.26.4
Requires-Dist: opencv-contrib-python==4.10.0.84
Requires-Dist: opencv-python==4.10.0.84
Requires-Dist: opt_einsum==3.4.0
Requires-Dist: optree==0.13.0
Requires-Dist: packaging==24.1
Requires-Dist: pandas==2.2.3
Requires-Dist: pillow==10.4.0
Requires-Dist: pip==24.2
Requires-Dist: protobuf==3.20.3
Requires-Dist: pyarrow==17.0.0
Requires-Dist: pycparser==2.22
Requires-Dist: pydeck==0.9.1
Requires-Dist: Pygments==2.18.0
Requires-Dist: pyparsing==3.1.4
Requires-Dist: python-dateutil==2.9.0.post0
Requires-Dist: pytz==2024.2
